spaceplot/__init__.py
spaceplot/_version.py
spaceplot-0.2.dist-info/LICENSE.txt
spaceplot-0.2.dist-info/METADATA
spaceplot-0.2.dist-info/WHEEL
spaceplot-0.2.dist-info/top_level.txt
spaceplot-0.2.dist-info/RECORD
