Metadata-Version: 2.1
Name: spaceplot
Version: 0.2
Summary: Plot multidimensional values against each other.
Home-page: https://spaceplot.readthedocs.io
Author: James Tocknell
Author-email: aragilar@gmail.com
License: 3-clause BSD
Keywords: matplotlib
Platform: UNKNOWN
Classifier: Development Status :: 3 - Alpha
Classifier: Intended Audience :: Developers
Classifier: Intended Audience :: Science/Research
Classifier: License :: OSI Approved :: BSD License
Classifier: Topic :: Scientific/Engineering
Classifier: Programming Language :: Python :: 3
Classifier: Programming Language :: Python :: 3.4
Classifier: Programming Language :: Python :: 3.5
Classifier: Programming Language :: Python :: 3.6
Classifier: Programming Language :: Python :: 3 :: Only
Requires-Python: >=3.4
Requires-Dist: matplotlib >=2.2
